pymedphys_utilities/__init__.py
pymedphys_utilities/_install_requires.py
pymedphys_utilities/_version.py
pymedphys_utilities/algorithms/__init__.py
pymedphys_utilities/algorithms/core.py
pymedphys_utilities/constants/__init__.py
pymedphys_utilities/constants/mlctypes.py
pymedphys_utilities/filehash/__init__.py
pymedphys_utilities/filehash/core.py
pymedphys_utilities/interpolate/__init__.py
pymedphys_utilities/interpolate/interpnd.py
pymedphys_utilities/interpolate/regulargrid.py
pymedphys_utilities/transforms/__init__.py
pymedphys_utilities/transforms/bipolar.py
pymedphys_utilities/utilities/__init__.py
pymedphys_utilities/utilities/compression.py
pymedphys_utilities/utilities/config.py
pymedphys_utilities/utilities/filesearch.py
pymedphys_utilities/utilities/filesystem.py
pymedphys_utilities-0.11.0.dist-info/LICENSE-AGPL-3.0-or-later
pymedphys_utilities-0.11.0.dist-info/LICENSE-Apache-2.0
pymedphys_utilities-0.11.0.dist-info/METADATA
pymedphys_utilities-0.11.0.dist-info/WHEEL
pymedphys_utilities-0.11.0.dist-info/top_level.txt
pymedphys_utilities-0.11.0.dist-info/RECORD
